rlpipes/__init__.py
rlpipes/cli.py
rlpipes/run_workflow.py
rlpipes/src/rlpipes.smk
rlpipes/src/data/available_genomes.tsv.xz
rlpipes/src/data/eff_gen_size.tsv.xz
rlpipes/src/data/wrangle_effgensize.R
rlpipes/src/envs/awscli.yaml
rlpipes/src/envs/bwa.yaml
rlpipes/src/envs/bwamem2.yaml
rlpipes/src/envs/clean.sh
rlpipes/src/envs/deeptools.yaml
rlpipes/src/envs/fastp.yaml
rlpipes/src/envs/macs2.yaml
rlpipes/src/envs/macs3.yaml
rlpipes/src/envs/rlseq.yaml
rlpipes/src/envs/rsem.yaml
rlpipes/src/envs/salmon.yaml
rlpipes/src/envs/samtools.yaml
rlpipes/src/envs/sratools.yaml
rlpipes/src/scripts/RLSeq.R
rlpipes-0.9.4.dist-info/LICENSE
rlpipes-0.9.4.dist-info/METADATA
rlpipes-0.9.4.dist-info/WHEEL
rlpipes-0.9.4.dist-info/entry_points.txt
rlpipes-0.9.4.dist-info/top_level.txt
rlpipes-0.9.4.dist-info/RECORD
