Metadata-Version: 2.1
Name: rlpipes
Version: 0.9.4
Summary: A standardized R-loop-mapping pipeline
Home-page: https://github.com/Bishop-Laboratory/RLPipes
Author: Henry Miller
Author-email: millerh1@livemail.uthscsa.edu
License: MIT
Platform: UNKNOWN
Classifier: License :: OSI Approved :: MIT License
Classifier: Programming Language :: Python :: 3
Classifier: Programming Language :: Python :: 3.7
Classifier: Programming Language :: Python :: 3.8
Classifier: Programming Language :: Python :: 3.9
License-File: LICENSE
Requires-Dist: Click
Requires-Dist: pysradb
Requires-Dist: pysam >=0.17.0
Requires-Dist: pyfastx
Requires-Dist: pandas ==1.2.0
